oemer/__init__.py
oemer/barline_extraction.py
oemer/bbox.py
oemer/build_label.py
oemer/build_system.py
oemer/classifier.py
oemer/constant.py
oemer/constant_min.py
oemer/convert_to_onnx.py
oemer/dewarp.py
oemer/draw_teaser.py
oemer/ete.py
oemer/exceptions.py
oemer/general_filtering_rules.py
oemer/inference.py
oemer/layers.py
oemer/logger.py
oemer/morph.py
oemer/note_group_extraction.py
oemer/notehead_extraction.py
oemer/rhythm_extraction.py
oemer/staffline_extraction.py
oemer/symbol_extraction.py
oemer/train.py
oemer/utils.py
oemer/checkpoints/seg_net/arch.json
oemer/checkpoints/seg_net/metadata.pkl
oemer/checkpoints/unet_big/arch.json
oemer/checkpoints/unet_big/metadata.pkl
oemer/models/__init__.py
oemer/models/naive_conv.py
oemer/models/unet.py
oemer/sklearn_models/clef.model
oemer/sklearn_models/rests.model
oemer/sklearn_models/rests_above8.model
oemer/sklearn_models/sfn.model
oemer-0.1.7.dist-info/LICENSE
oemer-0.1.7.dist-info/METADATA
oemer-0.1.7.dist-info/WHEEL
oemer-0.1.7.dist-info/entry_points.txt
oemer-0.1.7.dist-info/top_level.txt
oemer-0.1.7.dist-info/RECORD
