Metadata-Version: 2.1
Name: oemer
Version: 0.1.7
Summary: End-to-end Optical Music Recognition (OMR) system.
Home-page: https://github.com/BreezeWhite/oemer
Author: BreezeWhite
Author-email: miyasihta2010@tuta.io
License: License :: OSI Approved :: MIT License
Keywords: OMR,optical-music-recognition,AI,machine-learning,image-processing
Classifier: Intended Audience :: Science/Research
Classifier: Intended Audience :: Developers
Classifier: Intended Audience :: Education
Classifier: Intended Audience :: Information Technology
Classifier: License :: OSI Approved :: MIT License
Classifier: Programming Language :: Python :: 3
Classifier: Topic :: Education
Classifier: Topic :: Multimedia :: Graphics
Classifier: Topic :: Scientific/Engineering :: Artificial Intelligence
Classifier: Topic :: Scientific/Engineering :: Image Processing
Classifier: Topic :: Scientific/Engineering :: Image Recognition
Classifier: Topic :: Software Development :: Libraries :: Python Modules
Classifier: Topic :: Software Development :: Version Control :: Git
License-File: LICENSE
Requires-Dist: onnxruntime-gpu
Requires-Dist: opencv-python-headless >=4.5.3.56
Requires-Dist: matplotlib
Requires-Dist: pillow
Requires-Dist: scipy
Requires-Dist: scikit-learn >=1.2
Requires-Dist: types-Pillow
Requires-Dist: types-tensorflow
Requires-Dist: typing-extensions
Provides-Extra: tf
Requires-Dist: tensorflow ; extra == 'tf'
Requires-Dist: tf2onnx ; extra == 'tf'
